typed_redis/__init__.py
typed_redis/misc.py
typed_redis/redis.py
typed_redis/store.py
typed_redis-0.0.12.dist-info/LICENSE
typed_redis-0.0.12.dist-info/METADATA
typed_redis-0.0.12.dist-info/WHEEL
typed_redis-0.0.12.dist-info/entry_points.txt
typed_redis-0.0.12.dist-info/RECORD
