Metadata-Version: 2.3
Name: typed-redis
Version: 0.0.12
Summary: Pydantic Models for Redis
License: MIT
Author: Julien Kmec
Author-email: me@julien.dev
Requires-Python: >=3.11.0,<3.14
Classifier: License :: OSI Approved :: MIT License
Classifier: Programming Language :: Python :: 3
Classifier: Programming Language :: Python :: 3.11
Classifier: Programming Language :: Python :: 3.12
Classifier: Programming Language :: Python :: 3.13
Provides-Extra: dev
Requires-Dist: black (>=24.3.0) ; extra == "dev"
Requires-Dist: coverage (>=7.6) ; extra == "dev"
Requires-Dist: fakeredis (>=2.30.3)
Requires-Dist: isort (>=5.12.0) ; extra == "dev"
Requires-Dist: pydantic (>=2.11.7)
Requires-Dist: pydantic-super-model (>=1.0.3)
Requires-Dist: pylint (>=3.0.1) ; extra == "dev"
Requires-Dist: pytest (>=8.0) ; extra == "dev"
Requires-Dist: pytest-asyncio (>=0.23) ; extra == "dev"
Requires-Dist: pytest-cov (>=6.1.1) ; extra == "dev"
Requires-Dist: redis (>=6.4.0)
